sgqlc/__init__.py
sgqlc/codegen/__init__.py
sgqlc/codegen/__main__.py
sgqlc/codegen/operation.py
sgqlc/codegen/schema.py
sgqlc/endpoint/__init__.py
sgqlc/endpoint/base.py
sgqlc/endpoint/http.py
sgqlc/endpoint/requests.py
sgqlc/endpoint/websocket.py
sgqlc/introspection/__init__.py
sgqlc/introspection/__main__.py
sgqlc/operation/__init__.py
sgqlc/types/__init__.py
sgqlc/types/datetime.py
sgqlc/types/relay.py
sgqlc/types/uuid.py
artran_sgqlc-16.3.dist-info/LICENSE
artran_sgqlc-16.3.dist-info/METADATA
artran_sgqlc-16.3.dist-info/WHEEL
artran_sgqlc-16.3.dist-info/entry_points.txt
artran_sgqlc-16.3.dist-info/RECORD
