Metadata-Version: 2.1
Name: artran-sgqlc
Version: 16.3
Summary: Simple GraphQL Client. This is a fork that supports newer WebSocket servers.
Home-page: http://github.com/artran/sgqlc
License: ISC
Keywords: graphql,client,http,endpoint
Author: Gustavo Sverzut Barbieri
Author-email: barbieri@profusion.mobi
Requires-Python: >=3.7,<4.0
Classifier: Development Status :: 4 - Beta
Classifier: Environment :: Console
Classifier: Environment :: Web Environment
Classifier: Intended Audience :: Developers
Classifier: License :: OSI Approved
Classifier: License :: OSI Approved :: ISC License (ISCL)
Classifier: Operating System :: OS Independent
Classifier: Programming Language :: Python
Classifier: Programming Language :: Python :: 3
Classifier: Programming Language :: Python :: 3.7
Classifier: Programming Language :: Python :: 3.8
Classifier: Programming Language :: Python :: 3.9
Classifier: Programming Language :: Python :: 3.10
Classifier: Programming Language :: Python :: 3.11
Classifier: Topic :: Utilities
Provides-Extra: requests
Provides-Extra: websocket
Requires-Dist: graphql-core (>=3.1.7,<4.0.0)
Requires-Dist: requests ; extra == "requests"
Requires-Dist: websocket-client ; extra == "websocket"
Project-URL: Documentation, https://sgqlc.readthedocs.io/
Project-URL: Repository, http://github.com/artran/sgqlc
